AGS324/__init__.py
AGS324/ags4_standard_headers.json
AGS324/main.py
AGS324-0.1.1.dist-info/LICENSE
AGS324-0.1.1.dist-info/METADATA
AGS324-0.1.1.dist-info/WHEEL
AGS324-0.1.1.dist-info/top_level.txt
AGS324-0.1.1.dist-info/RECORD
