Metadata-Version: 2.1
Name: AGS324
Version: 0.1.1
Summary: A utility library for upgrading AGS 3.1 data to AGS 4
Author-email: Yixuan Zhong <yixuan.zhong.public@gmail.com>
License: LGPL-3.0
Project-URL: Homepage, https://github.com/yixuanzhong/AGS324
Project-URL: Bug Reports, https://github.com/yixuanzhong/AGS324/issues
Project-URL: Source, https://github.com/yixuanzhong/AGS324
Classifier: Development Status :: 3 - Alpha
Classifier: Intended Audience :: Developers
Classifier: Programming Language :: Python :: 3
Classifier: Programming Language :: Python :: 3.8
Classifier: Programming Language :: Python :: 3.9
Classifier: Programming Language :: Python :: 3.10
Classifier: Programming Language :: Python :: 3.11
Classifier: Programming Language :: Python :: 3.12
Classifier: Programming Language :: Python :: 3.13
Requires-Python: >=3.8
License-File: LICENSE
Requires-Dist: pandas>=1.5.3
